unit_system_py.py
unit_system_py-0.8.0rc9.dist-info/LICENSE
unit_system_py-0.8.0rc9.dist-info/METADATA
unit_system_py-0.8.0rc9.dist-info/WHEEL
unit_system_py-0.8.0rc9.dist-info/top_level.txt
unit_system_py-0.8.0rc9.dist-info/RECORD
