Metadata-Version: 2.1
Name: unit_system_py
Version: 0.8.0rc9
Summary: A simple unit system for python
Author-email: noasakurajin <dev@noasakurajin.de>
Project-URL: Homepage, https://github.com/noah1510/unit-system-generator
Project-URL: Bug Tracker, https://github.com/noah1510/unit-system-generator/issues
Classifier: Programming Language :: Python :: 3
Classifier: License :: OSI Approved :: GNU Lesser General Public License v3 (LGPLv3)
Classifier: Operating System :: OS Independent
Classifier: Topic :: Scientific/Engineering :: Physics
Classifier: Typing :: Typed
Requires-Python: >=3.8
License-File: LICENSE
